quantumlock_cli/__init__.py
quantumlock_cli/__main__.cpython-311-x86_64-linux-gnu.so
quantumlock_cli/anti_rollback.cpython-311-x86_64-linux-gnu.so
quantumlock_cli/client.cpython-311-x86_64-linux-gnu.so
quantumlock_cli/hybrid_validator.cpython-311-x86_64-linux-gnu.so
quantumlock_cli/keys.cpython-311-x86_64-linux-gnu.so
quantumlock_cli/license_v1.cpython-311-x86_64-linux-gnu.so
quantumlock_cli/main.cpython-311-x86_64-linux-gnu.so
quantumlock_cli/mldsa.cpython-311-x86_64-linux-gnu.so
quantumlock_cli/revocation_set.cpython-311-x86_64-linux-gnu.so
quantumlock_cli/serialization.cpython-311-x86_64-linux-gnu.so
quantumlock_cli/status_proof.cpython-311-x86_64-linux-gnu.so
quantumlock_cli/validator.cpython-311-x86_64-linux-gnu.so
quantumlock_cli/validator_v2.cpython-311-x86_64-linux-gnu.so
quantumlock_cli-1.0.4.dist-info/METADATA
quantumlock_cli-1.0.4.dist-info/WHEEL
quantumlock_cli-1.0.4.dist-info/entry_points.txt
quantumlock_cli-1.0.4.dist-info/RECORD
quantumlock_cli-1.0.4.dist-info/RECORD
